google_trans_simple.py
trs_google_lib-0.1.2.dist-info/METADATA
trs_google_lib-0.1.2.dist-info/WHEEL
trs_google_lib-0.1.2.dist-info/top_level.txt
trs_google_lib-0.1.2.dist-info/RECORD
